quality_covers-3.1.0.dist-info/WHEEL
quality_covers-3.1.0.dist-info/top_level.txt
quality_covers-3.1.0.dist-info/LICENSE
quality_covers-3.1.0.dist-info/RECORD
quality_covers-3.1.0.dist-info/METADATA
quality_covers.libs/libgomp-3300acd3.so.1.0.0
quality_covers/__init__.py
quality_covers/quality_covers.cpython-35m-x86_64-linux-gnu.so
quality_covers/matrice/__init__.py
quality_covers/matrice/matrice.py
