Metadata-Version: 2.1
Name: quality-covers
Version: 3.1.0
Summary: Python Package with quality covers C++ extension
Home-page: UNKNOWN
Author: Nicolas Gros
Author-email: nicolas.gros01@u-bourgogne.fr
License: UNKNOWN
Platform: UNKNOWN
Requires-Dist: numpy
